lxb_pylib/__init__.py
lxb_pylib/io/__init__.py
lxb_pylib/io/base.py
lxb_pylib/io/exceptions.py
lxb_pylib/io/export_utils.py
lxb_pylib/io/mysql.py
lxb_pylib/io/postgre.py
lxb_pylib/io/utils.py
lxb_pylib/utils/__init__.py
lxb_pylib/utils/loaders.py
lxb_pylib-1.3.1.dist-info/METADATA
lxb_pylib-1.3.1.dist-info/WHEEL
lxb_pylib-1.3.1.dist-info/top_level.txt
lxb_pylib-1.3.1.dist-info/RECORD
