Metadata-Version: 2.1
Name: lxb-pylib
Version: 1.3.1
Summary: Shared tools in multiple projects
Home-page: https://github.com/congvm.it/lxb_pylib
Author: Cong Vo
Author-email: congvm.it@gmail.com
Requires-Dist: mysql-connector-python (==8.0.31)
Requires-Dist: psycopg2-binary (==2.9.5)
Requires-Dist: numpy
Requires-Dist: pandas
Requires-Dist: pyyaml
Requires-Dist: pytest
